elmkit/__init__.py
elmkit/client.py
elmkit/messages.py
elmkit/parsing.py
elmkit/tools.py
elmkit/tracking.py
elmkit/utils.py
elmkit-0.1.0.dist-info/licenses/LICENSE
elmkit-0.1.0.dist-info/METADATA
elmkit-0.1.0.dist-info/WHEEL
elmkit-0.1.0.dist-info/top_level.txt
elmkit-0.1.0.dist-info/RECORD
