Metadata-Version: 2.4
Name: elmkit
Version: 0.1.0
Author-email: dontwakup <jfwu.ai@hotmail.com>
Requires-Python: >=3.13
License-File: LICENSE
Requires-Dist: openai>=1.99.3
Dynamic: license-file
